pycurtain/__init__.py
pycurtain/app.py
pycurtain/process/__init__.py
pycurtain/process/text_to_video_zoom.py
pycurtain/secrete/__init__.py
pycurtain/secrete/stuff.py
pycurtain/source/__init__.py
pycurtain/source/craiyon.py
pycurtain/source/dalle2.py
pycurtain/source/deep_ai.py
pycurtain/source/gpt3.py
pycurtain/source/replicate_stable_diffusion.py
pycurtain/source/stable_diffusion.py
pycurtain/source/protos/__init__.py
pycurtain/source/protos/image.py
pycurtain/source/protos/text.py
pycurtain/task/__init__.py
pycurtain/utility/__init__.py
pycurtain/utility/image.py
pycurtain/utility/video.py
pycurtain-0.0.91.dist-info/LICENSE.md
pycurtain-0.0.91.dist-info/METADATA
pycurtain-0.0.91.dist-info/WHEEL
pycurtain-0.0.91.dist-info/top_level.txt
pycurtain-0.0.91.dist-info/RECORD
