Metadata-Version: 2.1
Name: pycurtain
Version: 0.0.91
Summary: A community-maintained Python package for wrapping a variety of REST API calls for different AI art models.
Home-page: https://github.com/bin2ai/pycurtain
Author: bin2ai
License: MIT
Keywords: art,ai,deep learning,upscaling,img2img,text2img,style transfer,rest,rest api,wrapper,ML Model,GPT,Open Ai
Platform: UNKNOWN
Classifier: Development Status :: 1 - Planning
Classifier: Intended Audience :: Developers
Classifier: License :: OSI Approved :: MIT License
Classifier: Programming Language :: Python :: 3
Classifier: Operating System :: Microsoft :: Windows
License-File: LICENSE.md
Requires-Dist: imageio (>=2.22.4)
Requires-Dist: numpy (>=1.23.5)
Requires-Dist: openai (>=0.25.0)
Requires-Dist: pillow (>=9.3.0)
Requires-Dist: replicate (>=0.4.0)
Requires-Dist: requests (>=2.28.1)
Requires-Dist: stability-sdk (>=0.2.9)
Requires-Dist: transformers (>=4.25.1)
Provides-Extra: dev
Requires-Dist: check-manifest (>=0.48) ; extra == 'dev'
Requires-Dist: openai (>=0.25.0) ; extra == 'dev'
Requires-Dist: pytest (>=7.2.0) ; extra == 'dev'
